<annotation>
    <folder>images</folder>
    <filename>vehicle014103.jpg</filename>
    <size>
        <width>774</width>
        <height>518</height>
        <depth>3</depth>
    </size>
    <segmented>0</segmented>
    <object>
        <name>vehicle</name>
        <pose>Unspecified</pose>
        <truncated>0</truncated>
        <occluded>0</occluded>
        <difficult>0</difficult>
        <bndbox>
            <xmin>30</xmin>
            <ymin>69</ymin>
            <xmax>763</xmax>
            <ymax>374</ymax>
        </bndbox>
    </object>
</annotation>