<annotation>
    <folder>images</folder>
    <filename>vehicle004899.jpg</filename>
    <size>
        <width>424</width>
        <height>360</height>
        <depth>3</depth>
    </size>
    <segmented>0</segmented>
    <object>
        <name>vehicle</name>
        <pose>Unspecified</pose>
        <truncated>0</truncated>
        <occluded>0</occluded>
        <difficult>0</difficult>
        <bndbox>
            <xmin>8</xmin>
            <ymin>71</ymin>
            <xmax>421</xmax>
            <ymax>285</ymax>
        </bndbox>
    </object>
</annotation>