<annotation>
    <folder>images</folder>
    <filename>vehicle015777.jpg</filename>
    <size>
        <width>1500</width>
        <height>938</height>
        <depth>3</depth>
    </size>
    <segmented>0</segmented>
    <object>
        <name>vehicle</name>
        <pose>Unspecified</pose>
        <truncated>0</truncated>
        <occluded>0</occluded>
        <difficult>0</difficult>
        <bndbox>
            <xmin>226</xmin>
            <ymin>97</ymin>
            <xmax>1378</xmax>
            <ymax>848</ymax>
        </bndbox>
    </object>
</annotation>