<annotation>
    <folder>images</folder>
    <filename>vehicle002572.jpg</filename>
    <size>
        <width>800</width>
        <height>600</height>
        <depth>3</depth>
    </size>
    <segmented>0</segmented>
    <object>
        <name>vehicle</name>
        <pose>Unspecified</pose>
        <truncated>0</truncated>
        <occluded>0</occluded>
        <difficult>0</difficult>
        <bndbox>
            <xmin>37</xmin>
            <ymin>61</ymin>
            <xmax>756</xmax>
            <ymax>504</ymax>
        </bndbox>
    </object>
</annotation>